{
    "datetime": 1699486209,
    "filename": "PixelExperience_dreamlte-13.0-20231108-2330-UNOFFICIAL.zip",
    "id": "7636df5c6bf5d0725781657fbdb29e887021ac4d4a6982a9e2318c24bd33c447",
    "size": 1424844508,
    "url": "https://github.com/PixelExperience-Exynos/OTA/releases/download/PixelExperience_dreamlte-13.0-20231108-2330-UNOFFICIAL.zip/PixelExperience_dreamlte-13.0-20231108-2330-UNOFFICIAL.zip",
    "version": "thirteen",
    "filehash": "a09718fd0a0cc4ecc1f3d551dd38c685",
    "maintainers": [
        {
            "name": "ExpressLuke",
            "github_username": "expressluke",
            "ci_username": "expressluke",
            "versions": [
                "thirteen"
            ]
        }
    ],
    "error": false,
    "donate_url": "https://paypal.me/lukew594",
    "website_url": "https://github.com/PixelExperience-Exynos/OTA/releases",
    "news_url": "https://t.me/PixelExperience"
}
